{
  "version": "16.6.1",
  "ddragonVersion": "16.6.1",
  "cdragonVersion": "16.6",
  "championId": "Yone",
  "spellData": {
    "0": {
      "mSpellCalculations": {
        "QDamage": {
          "mFormulaParts": [
            {
              "mDataValue": "BaseDamage",
              "__type": "NamedDataValueCalculationPart"
            },
            {
              "mStat": 2,
              "mDataValue": "ADRatio",
              "__type": "StatByNamedDataValueCalculationPart"
            }
          ],
          "__type": "GameCalculation"
        },
        "TotalDamageCrit": {
          "mFormulaParts": [
            {
              "mDataValue": "BaseDamage",
              "__type": "NamedDataValueCalculationPart"
            },
            {
              "mStat": 2,
              "mSubpart": {
                "mStat": 9,
                "mDataValue": "ADRatio",
                "__type": "StatByNamedDataValueCalculationPart"
              },
              "__type": "StatBySubPartCalculationPart"
            }
          ],
          "__type": "GameCalculation"
        }
      }
    },
    "1": {
      "mSpellCalculations": {
        "WDamage": {
          "mFormulaParts": [
            {
              "mDataValue": "BaseDamage",
              "__type": "NamedDataValueCalculationPart"
            },
            {
              "mStat": 2,
              "mCoefficient": 1,
              "__type": "StatByCoefficientCalculationPart"
            }
          ],
          "__type": "GameCalculation"
        },
        "{8dfeb810}": {
          "mMultiplier": {
            "mStartValue": 0.20000000298023224,
            "mEndValue": 1,
            "__type": "ByCharLevelInterpolationCalculationPart"
          },
          "mFormulaParts": [
            {
              "mStat": 2,
              "mCoefficient": 1,
              "__type": "StatByCoefficientCalculationPart"
            }
          ],
          "__type": "GameCalculation"
        },
        "WShield": {
          "mFormulaParts": [
            {
              "mStartValue": 40,
              "mEndValue": 90,
              "__type": "ByCharLevelInterpolationCalculationPart"
            },
            {
              "mStat": 2,
              "mStatFormula": 2,
              "mDataValue": "ShieldBADRatio",
              "__type": "StatByNamedDataValueCalculationPart"
            }
          ],
          "__type": "GameCalculation"
        },
        "MinimumDamageMinions": {
          "mSimpleTooltipCalculationDisplay": 6,
          "mExpandedTooltipCalculationDisplay": 6,
          "mFormulaParts": [
            {
              "mLevel1Value": 30,
              "mBreakpoints": [
                {
                  "mBonusPerLevelAtAndAfter": 10,
                  "__type": "Breakpoint"
                },
                {
                  "mLevel": 9,
                  "mBonusPerLevelAtAndAfter": 20,
                  "__type": "Breakpoint"
                },
                {
                  "mLevel": 14,
                  "mBonusPerLevelAtAndAfter": 40,
                  "__type": "Breakpoint"
                }
              ],
              "__type": "ByCharLevelBreakpointsCalculationPart"
            }
          ],
          "__type": "GameCalculation"
        },
        "MonsterDamageCap": {
          "mFormulaParts": [
            {
              "values": [
                140,
                150,
                160,
                170,
                180,
                190,
                200,
                210,
                220,
                230,
                240,
                250,
                260,
                270,
                280,
                290,
                300,
                310,
                320,
                330,
                340,
                350,
                360,
                370,
                380,
                390,
                400,
                410,
                420,
                430,
                440
              ],
              "__type": "ByCharLevelFormulaCalculationPart"
            }
          ],
          "__type": "GameCalculation"
        }
      }
    },
    "2": {
      "mSpellCalculations": {
        "{df232269}": {
          "mFormulaParts": [
            {
              "mDataValue": "DeathmarkBase",
              "__type": "NamedDataValueCalculationPart"
            },
            {
              "mStat": 2,
              "mCoefficient": 0.25,
              "__type": "StatByCoefficientCalculationPart"
            }
          ],
          "__type": "GameCalculation"
        }
      }
    },
    "3": {
      "mSpellCalculations": {
        "Damage": {
          "mFormulaParts": [
            {
              "mDataValue": "BaseDamage",
              "__type": "NamedDataValueCalculationPart"
            },
            {
              "mStat": 2,
              "mStatFormula": 2,
              "mDataValue": "ADRatio",
              "__type": "StatByNamedDataValueCalculationPart"
            }
          ],
          "__type": "GameCalculation"
        },
        "TooltipDamage": {
          "mMultiplier": {
            "mNumber": 0.5,
            "__type": "NumberCalculationPart"
          },
          "mModifiedGameCalculation": "Damage",
          "__type": "GameCalculationModified"
        }
      }
    },
    "YoneQ": {
      "mSpellCalculations": {
        "QDamage": {
          "mFormulaParts": [
            {
              "mDataValue": "BaseDamage",
              "__type": "NamedDataValueCalculationPart"
            },
            {
              "mStat": 2,
              "mDataValue": "ADRatio",
              "__type": "StatByNamedDataValueCalculationPart"
            }
          ],
          "__type": "GameCalculation"
        },
        "TotalDamageCrit": {
          "mFormulaParts": [
            {
              "mDataValue": "BaseDamage",
              "__type": "NamedDataValueCalculationPart"
            },
            {
              "mStat": 2,
              "mSubpart": {
                "mStat": 9,
                "mDataValue": "ADRatio",
                "__type": "StatByNamedDataValueCalculationPart"
              },
              "__type": "StatBySubPartCalculationPart"
            }
          ],
          "__type": "GameCalculation"
        }
      }
    },
    "YoneW": {
      "mSpellCalculations": {
        "WDamage": {
          "mFormulaParts": [
            {
              "mDataValue": "BaseDamage",
              "__type": "NamedDataValueCalculationPart"
            },
            {
              "mStat": 2,
              "mCoefficient": 1,
              "__type": "StatByCoefficientCalculationPart"
            }
          ],
          "__type": "GameCalculation"
        },
        "{8dfeb810}": {
          "mMultiplier": {
            "mStartValue": 0.20000000298023224,
            "mEndValue": 1,
            "__type": "ByCharLevelInterpolationCalculationPart"
          },
          "mFormulaParts": [
            {
              "mStat": 2,
              "mCoefficient": 1,
              "__type": "StatByCoefficientCalculationPart"
            }
          ],
          "__type": "GameCalculation"
        },
        "WShield": {
          "mFormulaParts": [
            {
              "mStartValue": 40,
              "mEndValue": 90,
              "__type": "ByCharLevelInterpolationCalculationPart"
            },
            {
              "mStat": 2,
              "mStatFormula": 2,
              "mDataValue": "ShieldBADRatio",
              "__type": "StatByNamedDataValueCalculationPart"
            }
          ],
          "__type": "GameCalculation"
        },
        "MinimumDamageMinions": {
          "mSimpleTooltipCalculationDisplay": 6,
          "mExpandedTooltipCalculationDisplay": 6,
          "mFormulaParts": [
            {
              "mLevel1Value": 30,
              "mBreakpoints": [
                {
                  "mBonusPerLevelAtAndAfter": 10,
                  "__type": "Breakpoint"
                },
                {
                  "mLevel": 9,
                  "mBonusPerLevelAtAndAfter": 20,
                  "__type": "Breakpoint"
                },
                {
                  "mLevel": 14,
                  "mBonusPerLevelAtAndAfter": 40,
                  "__type": "Breakpoint"
                }
              ],
              "__type": "ByCharLevelBreakpointsCalculationPart"
            }
          ],
          "__type": "GameCalculation"
        },
        "MonsterDamageCap": {
          "mFormulaParts": [
            {
              "values": [
                140,
                150,
                160,
                170,
                180,
                190,
                200,
                210,
                220,
                230,
                240,
                250,
                260,
                270,
                280,
                290,
                300,
                310,
                320,
                330,
                340,
                350,
                360,
                370,
                380,
                390,
                400,
                410,
                420,
                430,
                440
              ],
              "__type": "ByCharLevelFormulaCalculationPart"
            }
          ],
          "__type": "GameCalculation"
        }
      }
    },
    "YoneE": {
      "mSpellCalculations": {
        "{df232269}": {
          "mFormulaParts": [
            {
              "mDataValue": "DeathmarkBase",
              "__type": "NamedDataValueCalculationPart"
            },
            {
              "mStat": 2,
              "mCoefficient": 0.25,
              "__type": "StatByCoefficientCalculationPart"
            }
          ],
          "__type": "GameCalculation"
        }
      }
    },
    "YoneR": {
      "mSpellCalculations": {
        "Damage": {
          "mFormulaParts": [
            {
              "mDataValue": "BaseDamage",
              "__type": "NamedDataValueCalculationPart"
            },
            {
              "mStat": 2,
              "mStatFormula": 2,
              "mDataValue": "ADRatio",
              "__type": "StatByNamedDataValueCalculationPart"
            }
          ],
          "__type": "GameCalculation"
        },
        "TooltipDamage": {
          "mMultiplier": {
            "mNumber": 0.5,
            "__type": "NumberCalculationPart"
          },
          "mModifiedGameCalculation": "Damage",
          "__type": "GameCalculationModified"
        }
      }
    },
    "YonePassive": {
      "mSpellCalculations": {
        "CurrentCritDamage": {
          "mExpandedTooltipCalculationDisplay": 6,
          "mFormulaParts": [
            {
              "mStat": 9,
              "mCoefficient": 1,
              "__type": "StatByCoefficientCalculationPart"
            }
          ],
          "mDisplayAsPercent": true,
          "__type": "GameCalculation"
        }
      }
    }
  }
}