{
  "version": "15.24.1",
  "lang": "ko_KR",
  "cdragonVersion": "15.24",
  "groups": [
    {
      "styleId": 8400,
      "styleName": "결의",
      "rows": [
        {
          "label": "공격",
          "perks": [
            {
              "id": 5008,
              "name": "적응형 능력치",
              "iconPath": "/lol-game-data/assets/v1/perk-images/StatMods/StatModsAdaptiveForceIcon.png",
              "shortDesc": "<lol-uikit-tooltipped-keyword key='LinkTooltip_Description_Adaptive'><font color='#48C4B7'>적응형 능력치</font></lol-uikit-tooltipped-keyword> +9",
              "longDesc": "<lol-uikit-tooltipped-keyword key='LinkTooltip_Description_Adaptive'><font color='#48C4B7'>적응형 능력치</font></lol-uikit-tooltipped-keyword> +9"
            },
            {
              "id": 5005,
              "name": "공격 속도",
              "iconPath": "/lol-game-data/assets/v1/perk-images/StatMods/StatModsAttackSpeedIcon.png",
              "shortDesc": "공격 속도 +10%",
              "longDesc": "공격 속도 +10%"
            },
            {
              "id": 5007,
              "name": "스킬 가속",
              "iconPath": "/lol-game-data/assets/v1/perk-images/StatMods/StatModsCDRScalingIcon.png",
              "shortDesc": "<lol-uikit-tooltipped-keyword key='LinkTooltip_Description_CDR'>스킬 가속</lol-uikit-tooltipped-keyword> +8 ",
              "longDesc": "<lol-uikit-tooltipped-keyword key='LinkTooltip_Description_CDR'>스킬 가속</lol-uikit-tooltipped-keyword> +8 "
            }
          ]
        },
        {
          "label": "유연",
          "perks": [
            {
              "id": 5008,
              "name": "적응형 능력치",
              "iconPath": "/lol-game-data/assets/v1/perk-images/StatMods/StatModsAdaptiveForceIcon.png",
              "shortDesc": "<lol-uikit-tooltipped-keyword key='LinkTooltip_Description_Adaptive'><font color='#48C4B7'>적응형 능력치</font></lol-uikit-tooltipped-keyword> +9",
              "longDesc": "<lol-uikit-tooltipped-keyword key='LinkTooltip_Description_Adaptive'><font color='#48C4B7'>적응형 능력치</font></lol-uikit-tooltipped-keyword> +9"
            },
            {
              "id": 5010,
              "name": "이동 속도",
              "iconPath": "/lol-game-data/assets/v1/perk-images/StatMods/StatModsMovementSpeedIcon.png",
              "shortDesc": "<lol-uikit-tooltipped-keyword key='LinkTooltip_Description_MS'>이동 속도</lol-uikit-tooltipped-keyword> +2.5%",
              "longDesc": "<lol-uikit-tooltipped-keyword key='LinkTooltip_Description_MS'>이동 속도</lol-uikit-tooltipped-keyword> +2.5%"
            },
            {
              "id": 5001,
              "name": "체력 증가",
              "iconPath": "/lol-game-data/assets/v1/perk-images/StatMods/StatModsHealthPlusIcon.png",
              "shortDesc": "체력 +10~180 (레벨에 비례)",
              "longDesc": "체력 +10~180 (레벨에 비례)"
            }
          ]
        },
        {
          "label": "방어",
          "perks": [
            {
              "id": 5011,
              "name": "체력",
              "iconPath": "/lol-game-data/assets/v1/perk-images/StatMods/StatModsHealthScalingIcon.png",
              "shortDesc": "체력 +65",
              "longDesc": "체력 +65"
            },
            {
              "id": 5013,
              "name": "강인함 및 둔화 저항",
              "iconPath": "/lol-game-data/assets/v1/perk-images/StatMods/StatModsTenacityIcon.png",
              "shortDesc": "강인함 및 둔화 저항 +15%",
              "longDesc": "강인함 및 둔화 저항 +15%"
            },
            {
              "id": 5001,
              "name": "체력 증가",
              "iconPath": "/lol-game-data/assets/v1/perk-images/StatMods/StatModsHealthPlusIcon.png",
              "shortDesc": "체력 +10~180 (레벨에 비례)",
              "longDesc": "체력 +10~180 (레벨에 비례)"
            }
          ]
        }
      ]
    },
    {
      "styleId": 8100,
      "styleName": "지배",
      "rows": [
        {
          "label": "공격",
          "perks": [
            {
              "id": 5008,
              "name": "적응형 능력치",
              "iconPath": "/lol-game-data/assets/v1/perk-images/StatMods/StatModsAdaptiveForceIcon.png",
              "shortDesc": "<lol-uikit-tooltipped-keyword key='LinkTooltip_Description_Adaptive'><font color='#48C4B7'>적응형 능력치</font></lol-uikit-tooltipped-keyword> +9",
              "longDesc": "<lol-uikit-tooltipped-keyword key='LinkTooltip_Description_Adaptive'><font color='#48C4B7'>적응형 능력치</font></lol-uikit-tooltipped-keyword> +9"
            },
            {
              "id": 5005,
              "name": "공격 속도",
              "iconPath": "/lol-game-data/assets/v1/perk-images/StatMods/StatModsAttackSpeedIcon.png",
              "shortDesc": "공격 속도 +10%",
              "longDesc": "공격 속도 +10%"
            },
            {
              "id": 5007,
              "name": "스킬 가속",
              "iconPath": "/lol-game-data/assets/v1/perk-images/StatMods/StatModsCDRScalingIcon.png",
              "shortDesc": "<lol-uikit-tooltipped-keyword key='LinkTooltip_Description_CDR'>스킬 가속</lol-uikit-tooltipped-keyword> +8 ",
              "longDesc": "<lol-uikit-tooltipped-keyword key='LinkTooltip_Description_CDR'>스킬 가속</lol-uikit-tooltipped-keyword> +8 "
            }
          ]
        },
        {
          "label": "유연",
          "perks": [
            {
              "id": 5008,
              "name": "적응형 능력치",
              "iconPath": "/lol-game-data/assets/v1/perk-images/StatMods/StatModsAdaptiveForceIcon.png",
              "shortDesc": "<lol-uikit-tooltipped-keyword key='LinkTooltip_Description_Adaptive'><font color='#48C4B7'>적응형 능력치</font></lol-uikit-tooltipped-keyword> +9",
              "longDesc": "<lol-uikit-tooltipped-keyword key='LinkTooltip_Description_Adaptive'><font color='#48C4B7'>적응형 능력치</font></lol-uikit-tooltipped-keyword> +9"
            },
            {
              "id": 5010,
              "name": "이동 속도",
              "iconPath": "/lol-game-data/assets/v1/perk-images/StatMods/StatModsMovementSpeedIcon.png",
              "shortDesc": "<lol-uikit-tooltipped-keyword key='LinkTooltip_Description_MS'>이동 속도</lol-uikit-tooltipped-keyword> +2.5%",
              "longDesc": "<lol-uikit-tooltipped-keyword key='LinkTooltip_Description_MS'>이동 속도</lol-uikit-tooltipped-keyword> +2.5%"
            },
            {
              "id": 5001,
              "name": "체력 증가",
              "iconPath": "/lol-game-data/assets/v1/perk-images/StatMods/StatModsHealthPlusIcon.png",
              "shortDesc": "체력 +10~180 (레벨에 비례)",
              "longDesc": "체력 +10~180 (레벨에 비례)"
            }
          ]
        },
        {
          "label": "방어",
          "perks": [
            {
              "id": 5011,
              "name": "체력",
              "iconPath": "/lol-game-data/assets/v1/perk-images/StatMods/StatModsHealthScalingIcon.png",
              "shortDesc": "체력 +65",
              "longDesc": "체력 +65"
            },
            {
              "id": 5013,
              "name": "강인함 및 둔화 저항",
              "iconPath": "/lol-game-data/assets/v1/perk-images/StatMods/StatModsTenacityIcon.png",
              "shortDesc": "강인함 및 둔화 저항 +15%",
              "longDesc": "강인함 및 둔화 저항 +15%"
            },
            {
              "id": 5001,
              "name": "체력 증가",
              "iconPath": "/lol-game-data/assets/v1/perk-images/StatMods/StatModsHealthPlusIcon.png",
              "shortDesc": "체력 +10~180 (레벨에 비례)",
              "longDesc": "체력 +10~180 (레벨에 비례)"
            }
          ]
        }
      ]
    },
    {
      "styleId": 8000,
      "styleName": "정밀",
      "rows": [
        {
          "label": "공격",
          "perks": [
            {
              "id": 5008,
              "name": "적응형 능력치",
              "iconPath": "/lol-game-data/assets/v1/perk-images/StatMods/StatModsAdaptiveForceIcon.png",
              "shortDesc": "<lol-uikit-tooltipped-keyword key='LinkTooltip_Description_Adaptive'><font color='#48C4B7'>적응형 능력치</font></lol-uikit-tooltipped-keyword> +9",
              "longDesc": "<lol-uikit-tooltipped-keyword key='LinkTooltip_Description_Adaptive'><font color='#48C4B7'>적응형 능력치</font></lol-uikit-tooltipped-keyword> +9"
            },
            {
              "id": 5005,
              "name": "공격 속도",
              "iconPath": "/lol-game-data/assets/v1/perk-images/StatMods/StatModsAttackSpeedIcon.png",
              "shortDesc": "공격 속도 +10%",
              "longDesc": "공격 속도 +10%"
            },
            {
              "id": 5007,
              "name": "스킬 가속",
              "iconPath": "/lol-game-data/assets/v1/perk-images/StatMods/StatModsCDRScalingIcon.png",
              "shortDesc": "<lol-uikit-tooltipped-keyword key='LinkTooltip_Description_CDR'>스킬 가속</lol-uikit-tooltipped-keyword> +8 ",
              "longDesc": "<lol-uikit-tooltipped-keyword key='LinkTooltip_Description_CDR'>스킬 가속</lol-uikit-tooltipped-keyword> +8 "
            }
          ]
        },
        {
          "label": "유연",
          "perks": [
            {
              "id": 5008,
              "name": "적응형 능력치",
              "iconPath": "/lol-game-data/assets/v1/perk-images/StatMods/StatModsAdaptiveForceIcon.png",
              "shortDesc": "<lol-uikit-tooltipped-keyword key='LinkTooltip_Description_Adaptive'><font color='#48C4B7'>적응형 능력치</font></lol-uikit-tooltipped-keyword> +9",
              "longDesc": "<lol-uikit-tooltipped-keyword key='LinkTooltip_Description_Adaptive'><font color='#48C4B7'>적응형 능력치</font></lol-uikit-tooltipped-keyword> +9"
            },
            {
              "id": 5010,
              "name": "이동 속도",
              "iconPath": "/lol-game-data/assets/v1/perk-images/StatMods/StatModsMovementSpeedIcon.png",
              "shortDesc": "<lol-uikit-tooltipped-keyword key='LinkTooltip_Description_MS'>이동 속도</lol-uikit-tooltipped-keyword> +2.5%",
              "longDesc": "<lol-uikit-tooltipped-keyword key='LinkTooltip_Description_MS'>이동 속도</lol-uikit-tooltipped-keyword> +2.5%"
            },
            {
              "id": 5001,
              "name": "체력 증가",
              "iconPath": "/lol-game-data/assets/v1/perk-images/StatMods/StatModsHealthPlusIcon.png",
              "shortDesc": "체력 +10~180 (레벨에 비례)",
              "longDesc": "체력 +10~180 (레벨에 비례)"
            }
          ]
        },
        {
          "label": "방어",
          "perks": [
            {
              "id": 5011,
              "name": "체력",
              "iconPath": "/lol-game-data/assets/v1/perk-images/StatMods/StatModsHealthScalingIcon.png",
              "shortDesc": "체력 +65",
              "longDesc": "체력 +65"
            },
            {
              "id": 5013,
              "name": "강인함 및 둔화 저항",
              "iconPath": "/lol-game-data/assets/v1/perk-images/StatMods/StatModsTenacityIcon.png",
              "shortDesc": "강인함 및 둔화 저항 +15%",
              "longDesc": "강인함 및 둔화 저항 +15%"
            },
            {
              "id": 5001,
              "name": "체력 증가",
              "iconPath": "/lol-game-data/assets/v1/perk-images/StatMods/StatModsHealthPlusIcon.png",
              "shortDesc": "체력 +10~180 (레벨에 비례)",
              "longDesc": "체력 +10~180 (레벨에 비례)"
            }
          ]
        }
      ]
    },
    {
      "styleId": 8200,
      "styleName": "마법",
      "rows": [
        {
          "label": "공격",
          "perks": [
            {
              "id": 5008,
              "name": "적응형 능력치",
              "iconPath": "/lol-game-data/assets/v1/perk-images/StatMods/StatModsAdaptiveForceIcon.png",
              "shortDesc": "<lol-uikit-tooltipped-keyword key='LinkTooltip_Description_Adaptive'><font color='#48C4B7'>적응형 능력치</font></lol-uikit-tooltipped-keyword> +9",
              "longDesc": "<lol-uikit-tooltipped-keyword key='LinkTooltip_Description_Adaptive'><font color='#48C4B7'>적응형 능력치</font></lol-uikit-tooltipped-keyword> +9"
            },
            {
              "id": 5005,
              "name": "공격 속도",
              "iconPath": "/lol-game-data/assets/v1/perk-images/StatMods/StatModsAttackSpeedIcon.png",
              "shortDesc": "공격 속도 +10%",
              "longDesc": "공격 속도 +10%"
            },
            {
              "id": 5007,
              "name": "스킬 가속",
              "iconPath": "/lol-game-data/assets/v1/perk-images/StatMods/StatModsCDRScalingIcon.png",
              "shortDesc": "<lol-uikit-tooltipped-keyword key='LinkTooltip_Description_CDR'>스킬 가속</lol-uikit-tooltipped-keyword> +8 ",
              "longDesc": "<lol-uikit-tooltipped-keyword key='LinkTooltip_Description_CDR'>스킬 가속</lol-uikit-tooltipped-keyword> +8 "
            }
          ]
        },
        {
          "label": "유연",
          "perks": [
            {
              "id": 5008,
              "name": "적응형 능력치",
              "iconPath": "/lol-game-data/assets/v1/perk-images/StatMods/StatModsAdaptiveForceIcon.png",
              "shortDesc": "<lol-uikit-tooltipped-keyword key='LinkTooltip_Description_Adaptive'><font color='#48C4B7'>적응형 능력치</font></lol-uikit-tooltipped-keyword> +9",
              "longDesc": "<lol-uikit-tooltipped-keyword key='LinkTooltip_Description_Adaptive'><font color='#48C4B7'>적응형 능력치</font></lol-uikit-tooltipped-keyword> +9"
            },
            {
              "id": 5010,
              "name": "이동 속도",
              "iconPath": "/lol-game-data/assets/v1/perk-images/StatMods/StatModsMovementSpeedIcon.png",
              "shortDesc": "<lol-uikit-tooltipped-keyword key='LinkTooltip_Description_MS'>이동 속도</lol-uikit-tooltipped-keyword> +2.5%",
              "longDesc": "<lol-uikit-tooltipped-keyword key='LinkTooltip_Description_MS'>이동 속도</lol-uikit-tooltipped-keyword> +2.5%"
            },
            {
              "id": 5001,
              "name": "체력 증가",
              "iconPath": "/lol-game-data/assets/v1/perk-images/StatMods/StatModsHealthPlusIcon.png",
              "shortDesc": "체력 +10~180 (레벨에 비례)",
              "longDesc": "체력 +10~180 (레벨에 비례)"
            }
          ]
        },
        {
          "label": "방어",
          "perks": [
            {
              "id": 5011,
              "name": "체력",
              "iconPath": "/lol-game-data/assets/v1/perk-images/StatMods/StatModsHealthScalingIcon.png",
              "shortDesc": "체력 +65",
              "longDesc": "체력 +65"
            },
            {
              "id": 5013,
              "name": "강인함 및 둔화 저항",
              "iconPath": "/lol-game-data/assets/v1/perk-images/StatMods/StatModsTenacityIcon.png",
              "shortDesc": "강인함 및 둔화 저항 +15%",
              "longDesc": "강인함 및 둔화 저항 +15%"
            },
            {
              "id": 5001,
              "name": "체력 증가",
              "iconPath": "/lol-game-data/assets/v1/perk-images/StatMods/StatModsHealthPlusIcon.png",
              "shortDesc": "체력 +10~180 (레벨에 비례)",
              "longDesc": "체력 +10~180 (레벨에 비례)"
            }
          ]
        }
      ]
    },
    {
      "styleId": 8300,
      "styleName": "영감",
      "rows": [
        {
          "label": "공격",
          "perks": [
            {
              "id": 5008,
              "name": "적응형 능력치",
              "iconPath": "/lol-game-data/assets/v1/perk-images/StatMods/StatModsAdaptiveForceIcon.png",
              "shortDesc": "<lol-uikit-tooltipped-keyword key='LinkTooltip_Description_Adaptive'><font color='#48C4B7'>적응형 능력치</font></lol-uikit-tooltipped-keyword> +9",
              "longDesc": "<lol-uikit-tooltipped-keyword key='LinkTooltip_Description_Adaptive'><font color='#48C4B7'>적응형 능력치</font></lol-uikit-tooltipped-keyword> +9"
            },
            {
              "id": 5005,
              "name": "공격 속도",
              "iconPath": "/lol-game-data/assets/v1/perk-images/StatMods/StatModsAttackSpeedIcon.png",
              "shortDesc": "공격 속도 +10%",
              "longDesc": "공격 속도 +10%"
            },
            {
              "id": 5007,
              "name": "스킬 가속",
              "iconPath": "/lol-game-data/assets/v1/perk-images/StatMods/StatModsCDRScalingIcon.png",
              "shortDesc": "<lol-uikit-tooltipped-keyword key='LinkTooltip_Description_CDR'>스킬 가속</lol-uikit-tooltipped-keyword> +8 ",
              "longDesc": "<lol-uikit-tooltipped-keyword key='LinkTooltip_Description_CDR'>스킬 가속</lol-uikit-tooltipped-keyword> +8 "
            }
          ]
        },
        {
          "label": "유연",
          "perks": [
            {
              "id": 5008,
              "name": "적응형 능력치",
              "iconPath": "/lol-game-data/assets/v1/perk-images/StatMods/StatModsAdaptiveForceIcon.png",
              "shortDesc": "<lol-uikit-tooltipped-keyword key='LinkTooltip_Description_Adaptive'><font color='#48C4B7'>적응형 능력치</font></lol-uikit-tooltipped-keyword> +9",
              "longDesc": "<lol-uikit-tooltipped-keyword key='LinkTooltip_Description_Adaptive'><font color='#48C4B7'>적응형 능력치</font></lol-uikit-tooltipped-keyword> +9"
            },
            {
              "id": 5010,
              "name": "이동 속도",
              "iconPath": "/lol-game-data/assets/v1/perk-images/StatMods/StatModsMovementSpeedIcon.png",
              "shortDesc": "<lol-uikit-tooltipped-keyword key='LinkTooltip_Description_MS'>이동 속도</lol-uikit-tooltipped-keyword> +2.5%",
              "longDesc": "<lol-uikit-tooltipped-keyword key='LinkTooltip_Description_MS'>이동 속도</lol-uikit-tooltipped-keyword> +2.5%"
            },
            {
              "id": 5001,
              "name": "체력 증가",
              "iconPath": "/lol-game-data/assets/v1/perk-images/StatMods/StatModsHealthPlusIcon.png",
              "shortDesc": "체력 +10~180 (레벨에 비례)",
              "longDesc": "체력 +10~180 (레벨에 비례)"
            }
          ]
        },
        {
          "label": "방어",
          "perks": [
            {
              "id": 5011,
              "name": "체력",
              "iconPath": "/lol-game-data/assets/v1/perk-images/StatMods/StatModsHealthScalingIcon.png",
              "shortDesc": "체력 +65",
              "longDesc": "체력 +65"
            },
            {
              "id": 5013,
              "name": "강인함 및 둔화 저항",
              "iconPath": "/lol-game-data/assets/v1/perk-images/StatMods/StatModsTenacityIcon.png",
              "shortDesc": "강인함 및 둔화 저항 +15%",
              "longDesc": "강인함 및 둔화 저항 +15%"
            },
            {
              "id": 5001,
              "name": "체력 증가",
              "iconPath": "/lol-game-data/assets/v1/perk-images/StatMods/StatModsHealthPlusIcon.png",
              "shortDesc": "체력 +10~180 (레벨에 비례)",
              "longDesc": "체력 +10~180 (레벨에 비례)"
            }
          ]
        }
      ]
    }
  ]
}