{
  "version": "16.2.1",
  "ddragonVersion": "16.2.1",
  "cdragonVersion": "16.1",
  "championId": "Katarina",
  "spellData": {
    "0": {
      "DataValues": {
        "BaseDamage": [
          45,
          80,
          115,
          150,
          185,
          220,
          255
        ],
        "BounceOffset": [
          350,
          350,
          350,
          350,
          350,
          350,
          350
        ],
        "BounceRadius": [
          450,
          450,
          450,
          450,
          450,
          450,
          450
        ],
        "MaxBounces": [
          2,
          2,
          2,
          2,
          2,
          2,
          2
        ],
        "QAPRatio": [
          0.4000000059604645,
          0.4000000059604645,
          0.4000000059604645,
          0.4000000059604645,
          0.4000000059604645,
          0.4000000059604645,
          0.4000000059604645
        ]
      },
      "mSpellCalculations": {
        "TotalDamage": {
          "mFormulaParts": [
            {
              "mDataValue": "BaseDamage",
              "__type": "NamedDataValueCalculationPart"
            },
            {
              "mDataValue": "QAPRatio",
              "__type": "StatByNamedDataValueCalculationPart"
            }
          ],
          "__type": "GameCalculation"
        }
      }
    },
    "2": {
      "DataValues": {
        "BaseDamage": [
          10,
          20,
          30,
          40,
          50,
          60,
          70
        ],
        "DataCooldown": [
          13,
          12,
          11,
          10,
          9,
          8,
          7
        ],
        "EADRatio": [
          0.4000000059604645,
          0.4000000059604645,
          0.4000000059604645,
          0.4000000059604645,
          0.4000000059604645,
          0.4000000059604645,
          0.4000000059604645
        ],
        "EAPRatio": [
          0.25,
          0.25,
          0.25,
          0.25,
          0.25,
          0.25,
          0.25
        ]
      },
      "mSpellCalculations": {
        "TotalDamage": {
          "mFormulaParts": [
            {
              "mDataValue": "BaseDamage",
              "__type": "NamedDataValueCalculationPart"
            },
            {
              "mDataValue": "EAPRatio",
              "__type": "StatByNamedDataValueCalculationPart"
            },
            {
              "mStat": 2,
              "mDataValue": "EADRatio",
              "__type": "StatByNamedDataValueCalculationPart"
            }
          ],
          "__type": "GameCalculation"
        },
        "DaggerCooldownReduction": {
          "mMultiplier": {
            "mPart1": {
              "__type": "CooldownMultiplierCalculationPart"
            },
            "mPart2": {
              "mDataValue": "DataCooldown",
              "__type": "NamedDataValueCalculationPart"
            },
            "__type": "ProductOfSubPartsCalculationPart"
          },
          "mModifiedGameCalculation": "{016cd4b3}",
          "__type": "GameCalculationModified"
        },
        "{016cd4b3}": {
          "mFormulaParts": [
            {
              "mLevel1Value": 0.7799999713897705,
              "mBreakpoints": [
                {
                  "mLevel": 6,
                  "mAdditionalBonusAtThisLevel": 0.05999999865889549,
                  "__type": "Breakpoint"
                },
                {
                  "mLevel": 11,
                  "mAdditionalBonusAtThisLevel": 0.05999999865889549,
                  "__type": "Breakpoint"
                },
                {
                  "mLevel": 16,
                  "mAdditionalBonusAtThisLevel": 0.05999999865889549,
                  "__type": "Breakpoint"
                },
                {
                  "mLevel": 21,
                  "mAdditionalBonusAtThisLevel": 0.03999999910593033,
                  "__type": "Breakpoint"
                }
              ],
              "__type": "ByCharLevelBreakpointsCalculationPart"
            }
          ],
          "mPrecision": 2,
          "__type": "GameCalculation"
        },
        "TooltipDaggerReduction": {
          "mFormulaParts": [
            {
              "mLevel1Value": 0.7799999713897705,
              "mBreakpoints": [
                {
                  "mLevel": 6,
                  "mAdditionalBonusAtThisLevel": 0.05999999865889549,
                  "__type": "Breakpoint"
                },
                {
                  "mLevel": 11,
                  "mAdditionalBonusAtThisLevel": 0.05999999865889549,
                  "__type": "Breakpoint"
                },
                {
                  "mLevel": 16,
                  "mAdditionalBonusAtThisLevel": 0.05999999865889549,
                  "__type": "Breakpoint"
                },
                {
                  "mLevel": 21,
                  "mAdditionalBonusAtThisLevel": 0.03999999910593033,
                  "__type": "Breakpoint"
                }
              ],
              "__type": "ByCharLevelBreakpointsCalculationPart"
            }
          ],
          "mDisplayAsPercent": true,
          "__type": "GameCalculation"
        }
      }
    },
    "3": {
      "DataValues": {
        "DamagePerTick": [
          12.5,
          25,
          37.5,
          50,
          62.5,
          75,
          87.5
        ],
        "TicksPerSecond": [
          6,
          6,
          6,
          6,
          6,
          6,
          6
        ],
        "Duration": [
          2.5,
          2.5,
          2.5,
          2.5,
          2.5,
          2.5,
          2.5
        ],
        "GrievousDuration": [
          3,
          3,
          3,
          3,
          3,
          3,
          3
        ],
        "GrievousAmount": [
          0.4000000059604645,
          0.4000000059604645,
          0.4000000059604645,
          0.4000000059604645,
          0.4000000059604645,
          0.4000000059604645,
          0.4000000059604645
        ],
        "OnHitRatio": [
          0.20000000298023224,
          0.25,
          0.30000001192092896,
          0.3499999940395355,
          0.4000000059604645,
          0.44999998807907104,
          0.5
        ],
        "RAPRatio": [
          0.1899999976158142,
          0.1899999976158142,
          0.1899999976158142,
          0.1899999976158142,
          0.1899999976158142,
          0.1899999976158142,
          0.1899999976158142
        ]
      },
      "mSpellCalculations": {
        "DamageCalc": {
          "mFormulaParts": [
            {
              "mDataValue": "DamagePerTick",
              "__type": "NamedDataValueCalculationPart"
            },
            {
              "mDataValue": "RAPRatio",
              "__type": "StatByNamedDataValueCalculationPart"
            }
          ],
          "__type": "GameCalculation"
        },
        "TotalDamageCalc": {
          "mMultiplier": {
            "mPart1": {
              "mDataValue": "TicksPerSecond",
              "__type": "NamedDataValueCalculationPart"
            },
            "mPart2": {
              "mDataValue": "Duration",
              "__type": "NamedDataValueCalculationPart"
            },
            "__type": "ProductOfSubPartsCalculationPart"
          },
          "mModifiedGameCalculation": "DamageCalc",
          "__type": "GameCalculationModified"
        },
        "ADDamageCalc": {
          "mFormulaParts": [
            {
              "mStat": 2,
              "mStatFormula": 2,
              "mSubpart": {
                "mSubparts": [
                  {
                    "mPart1": {
                      "mNumber": 0.1599999964237213,
                      "__type": "NumberCalculationPart"
                    },
                    "mPart2": {
                      "mSubparts": [
                        {
                          "mNumber": 1,
                          "__type": "NumberCalculationPart"
                        },
                        {
                          "mStat": 4,
                          "mStatFormula": 2,
                          "mCoefficient": 3.125,
                          "__type": "StatByCoefficientCalculationPart"
                        }
                      ],
                      "__type": "SumOfSubPartsCalculationPart"
                    },
                    "__type": "ProductOfSubPartsCalculationPart"
                  }
                ],
                "__type": "SumOfSubPartsCalculationPart"
              },
              "__type": "StatBySubPartCalculationPart"
            }
          ],
          "__type": "GameCalculation"
        },
        "TotalADDamageCalc": {
          "mMultiplier": {
            "mPart1": {
              "mDataValue": "TicksPerSecond",
              "__type": "NamedDataValueCalculationPart"
            },
            "mPart2": {
              "mDataValue": "Duration",
              "__type": "NamedDataValueCalculationPart"
            },
            "__type": "ProductOfSubPartsCalculationPart"
          },
          "mModifiedGameCalculation": "ADDamageCalc",
          "__type": "GameCalculationModified"
        }
      }
    },
    "KatarinaQ": {
      "DataValues": {
        "BaseDamage": [
          45,
          80,
          115,
          150,
          185,
          220,
          255
        ],
        "BounceOffset": [
          350,
          350,
          350,
          350,
          350,
          350,
          350
        ],
        "BounceRadius": [
          450,
          450,
          450,
          450,
          450,
          450,
          450
        ],
        "MaxBounces": [
          2,
          2,
          2,
          2,
          2,
          2,
          2
        ],
        "QAPRatio": [
          0.4000000059604645,
          0.4000000059604645,
          0.4000000059604645,
          0.4000000059604645,
          0.4000000059604645,
          0.4000000059604645,
          0.4000000059604645
        ]
      },
      "mSpellCalculations": {
        "TotalDamage": {
          "mFormulaParts": [
            {
              "mDataValue": "BaseDamage",
              "__type": "NamedDataValueCalculationPart"
            },
            {
              "mDataValue": "QAPRatio",
              "__type": "StatByNamedDataValueCalculationPart"
            }
          ],
          "__type": "GameCalculation"
        }
      }
    },
    "KatarinaEWrapper": {
      "DataValues": {
        "BaseDamage": [
          10,
          20,
          30,
          40,
          50,
          60,
          70
        ],
        "DataCooldown": [
          13,
          12,
          11,
          10,
          9,
          8,
          7
        ],
        "EADRatio": [
          0.4000000059604645,
          0.4000000059604645,
          0.4000000059604645,
          0.4000000059604645,
          0.4000000059604645,
          0.4000000059604645,
          0.4000000059604645
        ],
        "EAPRatio": [
          0.25,
          0.25,
          0.25,
          0.25,
          0.25,
          0.25,
          0.25
        ]
      },
      "mSpellCalculations": {
        "TotalDamage": {
          "mFormulaParts": [
            {
              "mDataValue": "BaseDamage",
              "__type": "NamedDataValueCalculationPart"
            },
            {
              "mDataValue": "EAPRatio",
              "__type": "StatByNamedDataValueCalculationPart"
            },
            {
              "mStat": 2,
              "mDataValue": "EADRatio",
              "__type": "StatByNamedDataValueCalculationPart"
            }
          ],
          "__type": "GameCalculation"
        },
        "DaggerCooldownReduction": {
          "mMultiplier": {
            "mPart1": {
              "__type": "CooldownMultiplierCalculationPart"
            },
            "mPart2": {
              "mDataValue": "DataCooldown",
              "__type": "NamedDataValueCalculationPart"
            },
            "__type": "ProductOfSubPartsCalculationPart"
          },
          "mModifiedGameCalculation": "{016cd4b3}",
          "__type": "GameCalculationModified"
        },
        "{016cd4b3}": {
          "mFormulaParts": [
            {
              "mLevel1Value": 0.7799999713897705,
              "mBreakpoints": [
                {
                  "mLevel": 6,
                  "mAdditionalBonusAtThisLevel": 0.05999999865889549,
                  "__type": "Breakpoint"
                },
                {
                  "mLevel": 11,
                  "mAdditionalBonusAtThisLevel": 0.05999999865889549,
                  "__type": "Breakpoint"
                },
                {
                  "mLevel": 16,
                  "mAdditionalBonusAtThisLevel": 0.05999999865889549,
                  "__type": "Breakpoint"
                },
                {
                  "mLevel": 21,
                  "mAdditionalBonusAtThisLevel": 0.03999999910593033,
                  "__type": "Breakpoint"
                }
              ],
              "__type": "ByCharLevelBreakpointsCalculationPart"
            }
          ],
          "mPrecision": 2,
          "__type": "GameCalculation"
        },
        "TooltipDaggerReduction": {
          "mFormulaParts": [
            {
              "mLevel1Value": 0.7799999713897705,
              "mBreakpoints": [
                {
                  "mLevel": 6,
                  "mAdditionalBonusAtThisLevel": 0.05999999865889549,
                  "__type": "Breakpoint"
                },
                {
                  "mLevel": 11,
                  "mAdditionalBonusAtThisLevel": 0.05999999865889549,
                  "__type": "Breakpoint"
                },
                {
                  "mLevel": 16,
                  "mAdditionalBonusAtThisLevel": 0.05999999865889549,
                  "__type": "Breakpoint"
                },
                {
                  "mLevel": 21,
                  "mAdditionalBonusAtThisLevel": 0.03999999910593033,
                  "__type": "Breakpoint"
                }
              ],
              "__type": "ByCharLevelBreakpointsCalculationPart"
            }
          ],
          "mDisplayAsPercent": true,
          "__type": "GameCalculation"
        }
      }
    },
    "KatarinaR": {
      "DataValues": {
        "DamagePerTick": [
          12.5,
          25,
          37.5,
          50,
          62.5,
          75,
          87.5
        ],
        "TicksPerSecond": [
          6,
          6,
          6,
          6,
          6,
          6,
          6
        ],
        "Duration": [
          2.5,
          2.5,
          2.5,
          2.5,
          2.5,
          2.5,
          2.5
        ],
        "GrievousDuration": [
          3,
          3,
          3,
          3,
          3,
          3,
          3
        ],
        "GrievousAmount": [
          0.4000000059604645,
          0.4000000059604645,
          0.4000000059604645,
          0.4000000059604645,
          0.4000000059604645,
          0.4000000059604645,
          0.4000000059604645
        ],
        "OnHitRatio": [
          0.20000000298023224,
          0.25,
          0.30000001192092896,
          0.3499999940395355,
          0.4000000059604645,
          0.44999998807907104,
          0.5
        ],
        "RAPRatio": [
          0.1899999976158142,
          0.1899999976158142,
          0.1899999976158142,
          0.1899999976158142,
          0.1899999976158142,
          0.1899999976158142,
          0.1899999976158142
        ]
      },
      "mSpellCalculations": {
        "DamageCalc": {
          "mFormulaParts": [
            {
              "mDataValue": "DamagePerTick",
              "__type": "NamedDataValueCalculationPart"
            },
            {
              "mDataValue": "RAPRatio",
              "__type": "StatByNamedDataValueCalculationPart"
            }
          ],
          "__type": "GameCalculation"
        },
        "TotalDamageCalc": {
          "mMultiplier": {
            "mPart1": {
              "mDataValue": "TicksPerSecond",
              "__type": "NamedDataValueCalculationPart"
            },
            "mPart2": {
              "mDataValue": "Duration",
              "__type": "NamedDataValueCalculationPart"
            },
            "__type": "ProductOfSubPartsCalculationPart"
          },
          "mModifiedGameCalculation": "DamageCalc",
          "__type": "GameCalculationModified"
        },
        "ADDamageCalc": {
          "mFormulaParts": [
            {
              "mStat": 2,
              "mStatFormula": 2,
              "mSubpart": {
                "mSubparts": [
                  {
                    "mPart1": {
                      "mNumber": 0.1599999964237213,
                      "__type": "NumberCalculationPart"
                    },
                    "mPart2": {
                      "mSubparts": [
                        {
                          "mNumber": 1,
                          "__type": "NumberCalculationPart"
                        },
                        {
                          "mStat": 4,
                          "mStatFormula": 2,
                          "mCoefficient": 3.125,
                          "__type": "StatByCoefficientCalculationPart"
                        }
                      ],
                      "__type": "SumOfSubPartsCalculationPart"
                    },
                    "__type": "ProductOfSubPartsCalculationPart"
                  }
                ],
                "__type": "SumOfSubPartsCalculationPart"
              },
              "__type": "StatBySubPartCalculationPart"
            }
          ],
          "__type": "GameCalculation"
        },
        "TotalADDamageCalc": {
          "mMultiplier": {
            "mPart1": {
              "mDataValue": "TicksPerSecond",
              "__type": "NamedDataValueCalculationPart"
            },
            "mPart2": {
              "mDataValue": "Duration",
              "__type": "NamedDataValueCalculationPart"
            },
            "__type": "ProductOfSubPartsCalculationPart"
          },
          "mModifiedGameCalculation": "ADDamageCalc",
          "__type": "GameCalculationModified"
        }
      }
    },
    "KatarinaPassive": {
      "DataValues": {
        "ResetWindow": [
          3,
          3,
          3,
          3,
          3,
          3,
          3
        ],
        "ResetCDR": [
          15,
          15,
          15,
          15,
          15,
          15,
          15
        ],
        "DaggerRadius": [
          340,
          340,
          340,
          340,
          340,
          340,
          340
        ],
        "DaggerDuration": [
          4,
          4,
          4,
          4,
          4,
          4,
          4
        ],
        "BonusADRatio": [
          0.6000000238418579,
          0.6000000238418579,
          0.6000000238418579,
          0.6000000238418579,
          0.6000000238418579,
          0.6000000238418579,
          0.6000000238418579
        ]
      },
      "mSpellCalculations": {
        "TotalDamage": {
          "mFormulaParts": [
            {
              "mValues": [
                0,
                68.18461608886719,
                72.13845825195312,
                76.86154174804688,
                82.35384368896484,
                88.61538696289062,
                95.64615631103516,
                103.44615173339844,
                112.015380859375,
                121.35384368896484,
                131.46153259277344,
                142.3384552001953,
                153.984619140625,
                166.39999389648438,
                179.58460998535156,
                193.53846740722656,
                208.26153564453125,
                223.75384521484375,
                240.015380859375,
                257.046142578125,
                274.8461608886719,
                293.4153747558594,
                312.75384521484375,
                332.8615417480469,
                353.73846435546875,
                375.3846130371094,
                397.79998779296875,
                420.984619140625,
                444.9384765625,
                469.6615295410156,
                495.1538391113281
              ],
              "__type": "ByCharLevelFormulaCalculationPart"
            },
            {
              "mStat": 2,
              "mStatFormula": 2,
              "mDataValue": "BonusADRatio",
              "__type": "StatByNamedDataValueCalculationPart"
            },
            {
              "mSubpart": {
                "mLevel1Value": 0.699999988079071,
                "mBreakpoints": [
                  {
                    "mLevel": 6,
                    "mAdditionalBonusAtThisLevel": 0.10000000149011612,
                    "__type": "Breakpoint"
                  },
                  {
                    "mLevel": 11,
                    "mAdditionalBonusAtThisLevel": 0.10000000149011612,
                    "__type": "Breakpoint"
                  },
                  {
                    "mLevel": 16,
                    "mAdditionalBonusAtThisLevel": 0.10000000149011612,
                    "__type": "Breakpoint"
                  }
                ],
                "__type": "ByCharLevelBreakpointsCalculationPart"
              },
              "__type": "StatBySubPartCalculationPart"
            }
          ],
          "__type": "GameCalculation"
        },
        "{e1ba6b0f}": {
          "mFormulaParts": [
            {
              "mLevel1Value": 0.7799999713897705,
              "mBreakpoints": [
                {
                  "mLevel": 6,
                  "mAdditionalBonusAtThisLevel": 0.05999999865889549,
                  "__type": "Breakpoint"
                },
                {
                  "mLevel": 11,
                  "mAdditionalBonusAtThisLevel": 0.05999999865889549,
                  "__type": "Breakpoint"
                },
                {
                  "mLevel": 16,
                  "mAdditionalBonusAtThisLevel": 0.05999999865889549,
                  "__type": "Breakpoint"
                }
              ],
              "__type": "ByCharLevelBreakpointsCalculationPart"
            }
          ],
          "__type": "GameCalculation"
        }
      }
    }
  }
}